Workbook

Sheet QPS
B1: ABC RFQ# | C1: 56789 | D1: EST Trading Company | G1: TODAY | H1: =NOW() -> 46279.991
D3: Quotation Preview System | N3: Nature Of Quote
N4: RFQ NUMBER | O4: =C1 -> 56789
B5: Customer | D5: Vector Company | G5: Customer ID Ref | H5: 90876 | N5: CUSTOMER NAME | O5: =D5 -> Vector Company
B6: Ventor | D6: Xandar Sellers | G6: Vendor ID Ref | H6: 23098 | N6: PAYMENT TERMS - CUSTOMER | O6: Next 90 Days
B7: Currency | D7: SAR | G7: Date | H7: 46259
B8: Exchange Rate | D8: 25.05 | N8: VENDOR NAME | O8: =D6 -> Xandar Sellers
N9: PAYMENT TERMS - VENDOR | O9: 10% Down Payment
B11: DETAILS | E11: AMOUNT (RS.) | F11: PER% | G11: ESTIMATED PRICE | H11: ACTUAL PRICE | N11: Currency in Customer Quote | O11: Ruppes
B12: Ex- Work | E12: - | G12: =SUM(G36:G45) -> 63455 | H12: =G12*D8 -> 1589547.8
B13: Sea Frieght Charges | E13: 35000 | G13: =E13/$D$8 -> 1397.2056 | H13: =E13 -> 35000 | N13: QUOTE CALCULATIONS
B14: Third Party Inspection | E14: 85000 | G14: =E14/$D$8 -> 3393.2136 | H14: =E14 -> 85000 | N14: Price Quoted by the Vendor | O14: =H12 -> 1589547.8
B15: Insurance | E15: 25000 | G15: =E15/$D$8 -> 998.00399 | H15: =E15 -> 25000 | N15: Sea Frieght Charges | O15: =H13 -> 35000
B16: Custom & Port Charges | E16: 18000 | G16: =E16/$D$8 -> 718.56287 | H16: =E16 -> 18000 | N16: Third Party Inspection | O16: =H14 -> 85000
B17: Inland Transportation | E17: 45000 | G17: =E17/$D$8 -> 1796.4072 | H17: =E17 -> 45000 | N17: Insurance | O17: =H15 -> 25000
B18: Money Cost & Etc. | E18: 30000 | G18: =E18/$D$8 -> 1197.6048 | H18: =E18 -> 30000 | N18: Custom & Port Charges | O18: =H16 -> 18000
B19: Total Delivery Cost | E19: - | G19: =SUM(G13:G18) -> 9500.998 | H19: =SUM(H13:H18) -> 238000 | N19: Inland Transportation | O19: =H17 -> 45000
B20: Mark-Up (Ex-Work & Cost) | E20: 0.5 | G20: =G12*$E$20 -> 31727.5 | H20: =H12*$E$20 -> 794773.88 | N20: Money Cost & Etc. | O20: =H18 -> 30000
B21: Overall Price (After Mark-Up) | E21: - | G21: =SUM(G12,G19,G20) -> 104683.5 | H21: =SUM(H12,H19,H20) -> 2622321.6 | N21: Total cost | O21: =SUM(O14:O20) -> 1827547.8
N22: Profit Gross | O22: =I26-O21 -> 794773.87
N23: Gross Profit Margin | O23: =O22/H21 -> 0.30308024
H24: Cost% of Sell Price | I24: =I25 -> 0.60616049 | N24: GPM Status | O24: =IF(O23>=50%,"EXCELLENT",IF(O23>=40%,"VERY GOOD",IF(O23>=30%,"GOOD",IF(O23>=20%,"AVERAGE",IF(O23<20%,"LOW"))))) -> GOOD
B25: Quote Validity | D25: 90 DAYS | H25: Cost-to-Sales Ratio | I25: =H12/H21 -> 0.60616049 | N25: Total Amount Include All Expences | O25: =H21 -> 2622321.6
B26: Prepared By | D26: CHITI | H26: Total Cost Selling Price | I26: =SUM(K36:K45) -> 2622321.6
B27: Approved By | D27: VIJAY
B28: Vendor P.O. ID | D28: 134567
B29: ABC Comp. P.O ID | D29: 86643
E32: Quotation
F34: VENDOR CURRENCY | H34: CURRENCY CONVERSION | J34: SELLING PRICE
B35: SL.NO | C35: ITEM CODE | D35: PRODUCTS DESCRIP. | E35: QUANTITY | F35: UNIT COST | G35: TOTAL PRICE | H35: UNIT COST(RS.) | I35: TOTAL PRICE (RS.) | J35: Selling Price/Unit(Rs.) | K35: Total Selling Price(Rs.) | L35: Approx. Price(Rs.) / Unit
B36: 1 | C36: PRD-001 | D36: INDUSTRIAL AIR COMP. | E36: 3 | F36: 2450 | G36: =E36*F36 -> 7350 | H36: =F36*$D$8 -> 61372.5 | I36: =H36*E36 -> 184117.5 | J36: =K36/E36 -> 101247.94 | K36: =I36/($I$25) -> 303743.82 | L36: 101250
B37: 2 | C37: PRD-002 | D37: HYDRAULIC PUMP | E37: 4 | F37: 1875 | G37: =E37*F37 -> 7500 | H37: =F37*$D$8 -> 46968.75 | I37: =H37*E37 -> 187875 | J37: =K37/E37 -> 77485.668 | K37: =I37/($I$25) -> 309942.67 | L37: 77500
B38: 3 | C38: PRD-003 | D38: ELECTRIC MOTOR 5HP | E38: 6 | F38: 980 | G38: =E38*F38 -> 5880 | H38: =F38*$D$8 -> 24549 | I38: =H38*E38 -> 147294 | J38: =K38/E38 -> 40499.176 | K38: =I38/($I$25) -> 242995.05 | L38: 40500
B39: 4 | C39: PRD-004 | D39: STAINLESS STEEL VALVE | E39: 12 | F39: 325 | G39: =E39*F39 -> 3900 | H39: =F39*$D$8 -> 8141.25 | I39: =H39*E39 -> 97695 | J39: =K39/E39 -> 13430.849 | K39: =I39/($I$25) -> 161170.19 | L39: 13450
B40: 5 | C40: PRD-005 | D40: PRESSURE GUAGE | E40: 15 | F40: 145 | G40: =E40*F40 -> 2175 | H40: =F40*$D$8 -> 3632.25 | I40: =H40*E40 -> 54483.75 | J40: =K40/E40 -> 5992.225 | K40: =I40/($I$25) -> 89883.375 | L40: 6000
B41: 6 | C41: PRD-006 | D41: CENTRIFUGAL PUMP | E41: 2 | F41: 3250 | G41: =E41*F41 -> 6500 | H41: =F41*$D$8 -> 81412.5 | I41: =H41*E41 -> 162825 | J41: =K41/E41 -> 134308.49 | K41: =I41/($I$25) -> 268616.98 | L41: 135000
B42: 7 | C42: PRD-007 | D42: GEAR BOX ASSEMBLY | E42: 5 | F42: 1620 | G42: =E42*F42 -> 8100 | H42: =F42*$D$8 -> 40581 | I42: =H42*E42 -> 202905 | J42: =K42/E42 -> 66947.617 | K42: =I42/($I$25) -> 334738.08 | L42: 67000
B43: 8 | C43: PRD-008 | D43: HEAT EXCHANGER | E43: 2 | F43: 4800 | G43: =E43*F43 -> 9600 | H43: =F43*$D$8 -> 120240 | I43: =H43*E43 -> 240480 | J43: =K43/E43 -> 198363.31 | K43: =I43/($I$25) -> 396726.62 | L43: 199000
B44: 9 | C44: PRD-009 | D44: INDUSTRIAL FAN | E44: 8 | F44: 750 | G44: =E44*F44 -> 6000 | H44: =F44*$D$8 -> 18787.5 | I44: =H44*E44 -> 150300 | J44: =K44/E44 -> 30994.267 | K44: =I44/($I$25) -> 247954.14 | L44: 31000
B45: 10 | C45: PRD-010 | D45: CONTROL PANEL | E45: 3 | F45: 2150 | G45: =E45*F45 -> 6450 | H45: =F45*$D$8 -> 53857.5 | I45: =H45*E45 -> 161572.5 | J45: =K45/E45 -> 88850.232 | K45: =I45/($I$25) -> 266550.7 | L45: 89000

Sheet FINAL QUOTE
F2: FINAL QUOTE
B4: Sl.No. | C4: ITEM ID | D4: DESCRIPTION | E4: UNIT | F4: QUANTITY | G4: UNIT COST | H4: TOTAL COST | I4: REMARKS
B5: 1 | C5: =QPS!C36 -> PRD-001 | D5: =QPS!D36 -> INDUSTRIAL AIR COMP. | E5: EA | F5: =QPS!E36 -> 3 | G5: =QPS!L36 -> 101250 | H5: =F5*G5 -> 303750 | I5: EX-STOCK
B6: 2 | C6: =QPS!C37 -> PRD-002 | D6: =QPS!D37 -> HYDRAULIC PUMP | E6: EA | F6: =QPS!E37 -> 4 | G6: =QPS!L37 -> 77500 | H6: =F6*G6 -> 310000 | I6: EX-STOCK
B7: 3 | C7: =QPS!C38 -> PRD-003 | D7: =QPS!D38 -> ELECTRIC MOTOR 5HP | E7: EA | F7: =QPS!E38 -> 6 | G7: =QPS!L38 -> 40500 | H7: =F7*G7 -> 243000 | I7: EX-STOCK
B8: 4 | C8: =QPS!C39 -> PRD-004 | D8: =QPS!D39 -> STAINLESS STEEL VALVE | E8: EA | F8: =QPS!E39 -> 12 | G8: =QPS!L39 -> 13450 | H8: =F8*G8 -> 161400 | I8: EX-STOCK
B9: 5 | C9: =QPS!C40 -> PRD-005 | D9: =QPS!D40 -> PRESSURE GUAGE | E9: EA | F9: =QPS!E40 -> 15 | G9: =QPS!L40 -> 6000 | H9: =F9*G9 -> 90000 | I9: EX-STOCK
B10: 6 | C10: =QPS!C41 -> PRD-006 | D10: =QPS!D41 -> CENTRIFUGAL PUMP | E10: EA | F10: =QPS!E41 -> 2 | G10: =QPS!L41 -> 135000 | H10: =F10*G10 -> 270000 | I10: EX-STOCK
B11: 7 | C11: =QPS!C42 -> PRD-007 | D11: =QPS!D42 -> GEAR BOX ASSEMBLY | E11: EA | F11: =QPS!E42 -> 5 | G11: =QPS!L42 -> 67000 | H11: =F11*G11 -> 335000 | I11: EX-STOCK
B12: 8 | C12: =QPS!C43 -> PRD-008 | D12: =QPS!D43 -> HEAT EXCHANGER | E12: EA | F12: =QPS!E43 -> 2 | G12: =QPS!L43 -> 199000 | H12: =F12*G12 -> 398000 | I12: EX-STOCK
B13: 9 | C13: =QPS!C44 -> PRD-009 | D13: =QPS!D44 -> INDUSTRIAL FAN | E13: EA | F13: =QPS!E44 -> 8 | G13: =QPS!L44 -> 31000 | H13: =F13*G13 -> 248000 | I13: EX-STOCK
B14: 10 | C14: =QPS!C45 -> PRD-010 | D14: =QPS!D45 -> CONTROL PANEL | E14: EA | F14: =QPS!E45 -> 3 | G14: =QPS!L45 -> 89000 | H14: =F14*G14 -> 267000 | I14: EX-STOCK
F15: TOTAL PRICE W/O TAX | H15: =SUM(H5:H9) -> 1108150
F16: TAX | G16: 0.18 | H16: =H15*G16 -> 199467
F17: TOTAL PRICE | H17: =SUM(H15:H16) -> 1307617
